i18ntools/__init__.py
i18ntools/parse_i18n_file.py
i18ntools/sort_i18n_file.py
i18ntools/translate.py
i18ntools/translate_missing.py
i18ntools-0.2.2.dist-info/licenses/LICENSE
i18ntools-0.2.2.dist-info/METADATA
i18ntools-0.2.2.dist-info/WHEEL
i18ntools-0.2.2.dist-info/entry_points.txt
i18ntools-0.2.2.dist-info/top_level.txt
i18ntools-0.2.2.dist-info/RECORD
