Metadata-Version: 2.4
Name: i18ntools
Version: 0.2.2
Summary: i18ntools helps translate Java properties i18n files using Azure Cognitive Services Translator
Author-email: Tyler VanZanten <tvanzanten@hypercision.com>
License-Expression: MIT
Project-URL: Homepage, https://github.com/hypercision/i18ntools
Project-URL: Bug Reports, https://github.com/hypercision/i18ntools/issues
Project-URL: Source, https://github.com/hypercision/i18ntools
Classifier: Programming Language :: Python :: 3
Classifier: Programming Language :: Python :: 3.10
Classifier: Programming Language :: Python :: 3.11
Classifier: Programming Language :: Python :: 3.12
Classifier: Programming Language :: Python :: 3.13
Classifier: Programming Language :: Python :: 3.14
Classifier: Operating System :: OS Independent
Classifier: Development Status :: 5 - Production/Stable
Requires-Python: >=3.10
License-File: LICENSE
Requires-Dist: requests
Provides-Extra: dev
Requires-Dist: black; extra == "dev"
Provides-Extra: test
Requires-Dist: pytest; extra == "test"
Requires-Dist: vcrpy; extra == "test"
Requires-Dist: tox; extra == "test"
Dynamic: license-file
